crewai_arcade/__init__.py
crewai_arcade/_utilities.py
crewai_arcade/manager.py
crewai_arcade/py.typed
crewai_arcade/structured.py
crewai_arcade-0.1.1.dist-info/LICENSE
crewai_arcade-0.1.1.dist-info/METADATA
crewai_arcade-0.1.1.dist-info/WHEEL
crewai_arcade-0.1.1.dist-info/RECORD
