Metadata-Version: 2.1
Name: crewai-arcade
Version: 0.1.1
Summary: An integration package connecting Arcade and CrewAI
Home-page: https://github.com/arcadeai/arcade-ai/tree/main/contrib/crewai
License: MIT
Author: Arcade
Author-email: dev@arcade.dev
Requires-Python: >=3.10,<3.13
Classifier: License :: OSI Approved :: MIT License
Classifier: Programming Language :: Python :: 3
Classifier: Programming Language :: Python :: 3.10
Classifier: Programming Language :: Python :: 3.11
Classifier: Programming Language :: Python :: 3.12
Requires-Dist: arcadepy (>=1.0.0,<2.0.0)
Requires-Dist: crewai (>=0.1.0,<1.0.0)
Requires-Dist: pydantic (>=2.0.0,<3.0.0)
Project-URL: Repository, https://github.com/arcadeai/arcade-ai/tree/main/contrib/crewai
